[
	{
		"date": "10.11.2024",
		"title": "Day 1 &#127881",
		"content": "this is a big silly test",
		"major": false,
		"images": 1,
		"image_url": [
			"/temp_logo.png"
		],
		"imageText": [
			"text1"
		]
	},

	{
		"date": "20.11.2024",
		"title": "Day 2 &#127881",
		"content": "this is a big sillyer test",
		"major": false,
		"images": 2,
		"image_url": [
			"/temp_logo.png",
			"/temp_logo.png"
		],
		"imageText": [
			"text2",
			"text3"
		]
	},
	{
		"date": "21.11.2024",
		"title": "Day 3 &#127881",
		"content": "this is the big sillyist test",
		"major": true,
		"images": 0,
		"image_url": [],
		"imageText": []
	}
]
